fabcohort_test/__init__.py
fabcohort_test/app.py
fabcohort_test-0.1.2.dist-info/METADATA
fabcohort_test-0.1.2.dist-info/WHEEL
fabcohort_test-0.1.2.dist-info/entry_points.txt
fabcohort_test-0.1.2.dist-info/top_level.txt
fabcohort_test-0.1.2.dist-info/RECORD
