Metadata-Version: 2.1
Name: fabcohort-test
Version: 0.1.2
Summary: Demo of a simple way to use GitHub Actions to build your Python package, bump the version number, and publish it to GitHub releases and PyPI.org all with a single click of a button in the web interface.
Home-page: https://github.com/linliD/fabcohort_test
Project-URL: Bug Tracker, https://github.com/linliD/fabcohort_test/issues
Project-URL: Changelog, https://github.com/linliD/fabcohort_test/releases
Classifier: Programming Language :: Python :: 3
Classifier: License :: OSI Approved :: BSD License
Classifier: Intended Audience :: Developers
Requires-Python: >=3.6
